{
"type": "FeatureCollection",
"crs": { "type": "name", "properties": { "name": "urn:ogc:def:crs:OGC:1.3:CRS84" } },
                                                                                                                                  
"features": [
{ "type": "Feature", "properties": { "NAMOBJ": "Alun Alun Prawoto", "ALIAS": "Alun-alun", "WADMKD": "PRAWOTO", "WADMKC": "KECAMATAN SUKOLILO", "Sumber": "Toponim Deliniasi Batas Wilayah Administrasi Desa Secara Kartometrik BIG 2017" }, "geometry": { "type": "Point", "coordinates": [ 110.82750647308711, -6.962653363652858, 0.0 ] } },
{ "type": "Feature", "properties": { "NAMOBJ": "Kantor Desa Prawoto", "ALIAS": "Desa", "WADMKD": "PRAWOTO", "WADMKC": "KECAMATAN SUKOLILO", "Sumber": "Toponim Deliniasi Batas Wilayah Administrasi Desa Secara Kartometrik BIG 2017" }, "geometry": { "type": "Point", "coordinates": [ 110.82799638929067, -6.961900700111205, 0.0 ] } },
{ "type": "Feature", "properties": { "NAMOBJ": "Kantor Desa Wegil", "ALIAS": "Desa", "WADMKD": "WEGIL", "WADMKC": "KECAMATAN SUKOLILO", "Sumber": "Toponim Deliniasi Batas Wilayah Administrasi Desa Secara Kartometrik BIG 2017" }, "geometry": { "type": "Point", "coordinates": [ 110.85727261814715, -6.951648130166658, 0.0 ] } },
{ "type": "Feature", "properties": { "NAMOBJ": "Kantor Desa Kedungwinong", "ALIAS": "Desa", "WADMKD": "KEDUNGWINONG", "WADMKC": "KECAMATAN SUKOLILO", "Sumber": "Toponim Deliniasi Batas Wilayah Administrasi Desa Secara Kartometrik BIG 2017" }, "geometry": { "type": "Point", "coordinates": [ 110.89519696394491, -6.936502445899796, 0.0 ] } },
{ "type": "Feature", "properties": { "NAMOBJ": "Kantor Desa Baleadi", "ALIAS": "Desa", "WADMKD": "BALEADI", "WADMKC": "KECAMATAN SUKOLILO", "Sumber": "Toponim Deliniasi Batas Wilayah Administrasi Desa Secara Kartometrik BIG 2017" }, "geometry": { "type": "Point", "coordinates": [ 110.88750785792412, -6.932966377879347, 0.0 ] } },
{ "type": "Feature", "properties": { "NAMOBJ": "Kantor Camat Sukolilo", "ALIAS": "Camat", "WADMKD": "SUKOLILO", "WADMKC": "KECAMATAN SUKOLILO", "Sumber": "Toponim Deliniasi Batas Wilayah Administrasi Desa Secara Kartometrik BIG 2017" }, "geometry": { "type": "Point", "coordinates": [ 110.91913848431723, -6.930301942455406, 0.0 ] } },
{ "type": "Feature", "properties": { "NAMOBJ": "Puskesmas Sukolilo", "ALIAS": "Puskesmas", "WADMKD": "SUKOLILO", "WADMKC": "KECAMATAN SUKOLILO", "Sumber": "Toponim Deliniasi Batas Wilayah Administrasi Desa Secara Kartometrik BIG 2017" }, "geometry": { "type": "Point", "coordinates": [ 110.92019444444442, -6.92947222222222, 0.0 ] } },
{ "type": "Feature", "properties": { "NAMOBJ": "Kantor Desa Sukolilo", "ALIAS": "Desa", "WADMKD": "SUKOLILO", "WADMKC": "KECAMATAN SUKOLILO", "Sumber": "Toponim Deliniasi Batas Wilayah Administrasi Desa Secara Kartometrik BIG 2017" }, "geometry": { "type": "Point", "coordinates": [ 110.9200335246631, -6.929414694788456, 0.0 ] } },
{ "type": "Feature", "properties": { "NAMOBJ": "Kantor Desa Gadudero", "ALIAS": "Desa", "WADMKD": "GADUDERO", "WADMKC": "KECAMATAN SUKOLILO", "Sumber": "Toponim Deliniasi Batas Wilayah Administrasi Desa Secara Kartometrik BIG 2017" }, "geometry": { "type": "Point", "coordinates": [ 110.92967450025283, -6.927180786237382, 0.0 ] } },
{ "type": "Feature", "properties": { "NAMOBJ": "Kantor Desa Wotan", "ALIAS": "Desa", "WADMKD": "WOTAN", "WADMKC": "KECAMATAN SUKOLILO", "Sumber": "Toponim Deliniasi Batas Wilayah Administrasi Desa Secara Kartometrik BIG 2017" }, "geometry": { "type": "Point", "coordinates": [ 110.90718379915846, -6.920724358658309, 0.0 ] } },
{ "type": "Feature", "properties": { "NAMOBJ": "Kantor Desa Kedungmulyo", "ALIAS": "Desa", "WADMKD": "KEDUMULYO", "WADMKC": "KECAMATAN SUKOLILO", "Sumber": "Toponim Deliniasi Batas Wilayah Administrasi Desa Secara Kartometrik BIG 2017" }, "geometry": { "type": "Point", "coordinates": [ 110.94817130771287, -6.918029449042383, 0.0 ] } },
{ "type": "Feature", "properties": { "NAMOBJ": "Kantor Desa Baturejo", "ALIAS": "Desa", "WADMKD": "BATUREJO", "WADMKC": "KECAMATAN SUKOLILO", "Sumber": "Toponim Deliniasi Batas Wilayah Administrasi Desa Secara Kartometrik BIG 2017" }, "geometry": { "type": "Point", "coordinates": [ 110.91106015397462, -6.917224545362417, 0.0 ] } },
{ "type": "Feature", "properties": { "NAMOBJ": "Kantor Desa Cengkalsewu", "ALIAS": "Desa", "WADMKD": "CENGKALSEWU", "WADMKC": "KECAMATAN SUKOLILO", "Sumber": "Toponim Deliniasi Batas Wilayah Administrasi Desa Secara Kartometrik BIG 2017" }, "geometry": { "type": "Point", "coordinates": [ 110.96237407490399, -6.90865122145447, 0.0 ] } },
{ "type": "Feature", "properties": { "NAMOBJ": "Kantor Desa Kasiyan", "ALIAS": "Desa", "WADMKD": "KASIAN", "WADMKC": "KECAMATAN SUKOLILO", "Sumber": "Toponim Deliniasi Batas Wilayah Administrasi Desa Secara Kartometrik BIG 2017" }, "geometry": { "type": "Point", "coordinates": [ 110.94881188235387, -6.908226687636074, 0.0 ] } }
]
}
